{
  "title": "Huerto Hidrop贸nico",
  "image": null,
  "mobileHide": false,
  "mobileOrder": null,
  "configuration": {
    "description": "",
    "widgets": {
      "eb9cd148-fe64-9230-9a9a-3eda49a524d2": {
        "isSystemType": true,
        "bundleAlias": "analogue_gauges",
        "typeAlias": "temperature_gauge_canvas_gauges",
        "type": "latest",
        "title": "New widget",
        "image": null,
        "description": null,
        "sizeX": 7,
        "sizeY": 3,
        "config": {
          "datasources": [
            {
              "type": "entity",
              "name": null,
              "entityAliasId": "34c859bf-95f3-7c64-da8a-b5351c3d4281",
              "filterId": null,
              "dataKeys": [
                {
                  "name": "Temperatura",
                  "type": "timeseries",
                  "label": "Temperatura",
                  "color": "#2196f3",
                  "settings": {},
                  "_hash": 0.905537897117481
                }
              ]
            }
          ],
          "timewindow": {
            "displayValue": "",
            "selectedTab": 0,
            "realtime": {
              "realtimeType": 1,
              "interval": 1000,
              "timewindowMs": 60000,
              "quickInterval": "CURRENT_DAY"
            },
            "history": {
              "historyType": 0,
              "interval": 1000,
              "timewindowMs": 60000,
              "fixedTimewindow": {
                "startTimeMs": 1674305929899,
                "endTimeMs": 1674392329899
              },
              "quickInterval": "CURRENT_DAY"
            },
            "aggregation": {
              "type": "AVG",
              "limit": 2500
            }
          },
          "showTitle": false,
          "backgroundColor": "rgb(255, 255, 255)",
          "color": "rgba(0, 0, 0, 0.87)",
          "padding": "8px",
          "settings": {
            "startAngle": 45,
            "ticksAngle": 270,
            "needleCircleSize": 10,
            "defaultColor": "#e64a19",
            "minValue": -6,
            "maxValue": 50,
            "majorTicksCount": 8,
            "colorMajorTicks": "#444",
            "minorTicks": 7,
            "colorMinorTicks": "#666",
            "numbersFont": {
              "family": "Arial",
              "size": 18,
              "style": "normal",
              "weight": "normal",
              "color": "#263238"
            },
            "showUnitTitle": true,
            "unitTitle": "Temperatura",
            "titleFont": {
              "family": "Roboto",
              "size": 24,
              "style": "normal",
              "weight": "normal",
              "color": "#78909c"
            },
            "unitsFont": {
              "family": "Roboto",
              "size": 26,
              "style": "normal",
              "weight": "500",
              "color": "#37474f"
            },
            "valueBox": true,
            "valueInt": 3,
            "valueFont": {
              "family": "Roboto",
              "size": 40,
              "style": "normal",
              "weight": "500",
              "color": "#444",
              "shadowColor": "rgba(0,0,0,0.3)"
            },
            "colorValueBoxRect": "#888",
            "colorValueBoxRectEnd": "#666",
            "colorValueBoxBackground": "#babab2",
            "colorValueBoxShadow": "rgba(0,0,0,1)",
            "showBorder": false,
            "colorPlate": "#fff",
            "colorNeedleShadowUp": "rgba(2,255,255,0.2)",
            "colorNeedleShadowDown": "rgba(188,143,143,0.45)",
            "highlightsWidth": 10,
            "highlights": [
              {
                "from": -6,
                "to": 1,
                "color": "#90caf9"
              },
              {
                "from": 1,
                "to": 8,
                "color": "rgba(144, 202, 249, 0.66)"
              },
              {
                "from": 8,
                "to": 15,
                "color": "rgba(144, 202, 249, 0.33)"
              },
              {
                "from": 15,
                "to": 22,
                "color": "rgba(244, 67, 54, 0.2)"
              },
              {
                "from": 22,
                "to": 29,
                "color": "rgba(244, 67, 54, 0.4)"
              },
              {
                "from": 29,
                "to": 36,
                "color": "rgba(244, 67, 54, 0.6)"
              },
              {
                "from": 36,
                "to": 43,
                "color": "rgba(244, 67, 54, 0.8)"
              },
              {
                "from": 43,
                "to": 50,
                "color": "#f44336"
              }
            ],
            "animation": true,
            "animationDuration": 1500,
            "animationRule": "linear",
            "barStrokeWidth": 2.5,
            "colorBarStroke": "#b0bec5",
            "colorBar": "rgba(255, 255, 255, 0.4)",
            "colorBarEnd": "rgba(221, 221, 221, 0.38)",
            "colorBarProgress": "#90caf9",
            "colorBarProgressEnd": "#f44336"
          },
          "title": "New Thermometer scale",
          "dropShadow": true,
          "enableFullscreen": true,
          "titleStyle": {
            "fontSize": "16px",
            "fontWeight": 400
          },
          "useDashboardTimewindow": true,
          "widgetStyle": {},
          "widgetCss": "",
          "pageSize": 1024,
          "noDataDisplayMessage": "",
          "showLegend": false,
          "legendConfig": {
            "direction": "column",
            "position": "bottom",
            "sortDataKeys": false,
            "showMin": true,
            "showMax": true,
            "showAvg": false,
            "showTotal": false,
            "showLatest": false
          }
        },
        "row": 0,
        "col": 0,
        "id": "eb9cd148-fe64-9230-9a9a-3eda49a524d2"
      },
      "734af6a5-39ac-5637-c5a7-3bff34d1b5c6": {
        "isSystemType": true,
        "bundleAlias": "digital_gauges",
        "typeAlias": "neon_gauge_justgage",
        "type": "latest",
        "title": "New widget",
        "image": null,
        "description": null,
        "sizeX": 5,
        "sizeY": 3,
        "config": {
          "datasources": [
            {
              "type": "entity",
              "name": null,
              "entityAliasId": "34c859bf-95f3-7c64-da8a-b5351c3d4281",
              "filterId": null,
              "dataKeys": [
                {
                  "name": "Electroconductividad",
                  "type": "timeseries",
                  "label": "Electroconductividad",
                  "color": "#2196f3",
                  "settings": {},
                  "_hash": 0.9652272878946808
                }
              ]
            }
          ],
          "timewindow": {
            "displayValue": "",
            "selectedTab": 0,
            "realtime": {
              "realtimeType": 1,
              "interval": 1000,
              "timewindowMs": 60000,
              "quickInterval": "CURRENT_DAY"
            },
            "history": {
              "historyType": 0,
              "interval": 1000,
              "timewindowMs": 60000,
              "fixedTimewindow": {
                "startTimeMs": 1674305929899,
                "endTimeMs": 1674392329899
              },
              "quickInterval": "CURRENT_DAY"
            },
            "aggregation": {
              "type": "AVG",
              "limit": 2500
            }
          },
          "showTitle": false,
          "backgroundColor": "#000000",
          "color": "rgba(255, 254, 254, 0.87)",
          "padding": "0px",
          "settings": {
            "minValue": 0,
            "maxValue": 50,
            "gaugeType": "arc",
            "defaultColor": "#f3ff00",
            "gaugeWidthScale": 0.75,
            "neonGlowBrightness": 70,
            "dashThickness": 1,
            "roundedLineCap": false,
            "gaugeColor": "rgba(255,255,255,0.42)",
            "useFixedLevelColor": false,
            "levelColors": [],
            "showTitle": true,
            "title": "Electroconductividad",
            "titleFont": {
              "family": "Roboto",
              "size": 12,
              "style": "normal",
              "weight": "500"
            },
            "showUnitTitle": true,
            "unitTitle": "mS/cm",
            "showTimestamp": false,
            "labelFont": {
              "family": "Roboto",
              "size": 8,
              "style": "normal",
              "weight": "500"
            },
            "showValue": true,
            "valueFont": {
              "family": "Segment7Standard",
              "style": "normal",
              "weight": "500",
              "size": 32
            },
            "showMinMax": true,
            "minMaxFont": {
              "family": "Segment7Standard",
              "size": 12,
              "style": "normal",
              "weight": "500"
            },
            "showTicks": false,
            "animation": true,
            "animationDuration": 500,
            "animationRule": "linear"
          },
          "title": "Electroconductividad",
          "dropShadow": true,
          "enableFullscreen": true,
          "titleStyle": {
            "fontSize": "16px",
            "fontWeight": 400
          },
          "widgetStyle": {},
          "useDashboardTimewindow": true,
          "showLegend": false,
          "actions": {},
          "showTitleIcon": false,
          "titleTooltip": "",
          "widgetCss": "",
          "pageSize": 1024,
          "noDataDisplayMessage": "",
          "units": "",
          "decimals": 3,
          "legendConfig": {
            "direction": "column",
            "position": "bottom",
            "sortDataKeys": false,
            "showMin": false,
            "showMax": false,
            "showAvg": false,
            "showTotal": false,
            "showLatest": false
          }
        },
        "row": 0,
        "col": 0,
        "id": "734af6a5-39ac-5637-c5a7-3bff34d1b5c6"
      },
      "068d8187-65e0-8253-58c4-ff784dfd2948": {
        "isSystemType": true,
        "bundleAlias": "alarm_widgets",
        "typeAlias": "alarms_table",
        "type": "alarm",
        "title": "New widget",
        "image": null,
        "description": null,
        "sizeX": 10.5,
        "sizeY": 6.5,
        "config": {
          "timewindow": {
            "realtime": {
              "interval": 1000,
              "timewindowMs": 86400000
            },
            "aggregation": {
              "type": "NONE",
              "limit": 200
            }
          },
          "showTitle": true,
          "backgroundColor": "rgb(255, 255, 255)",
          "color": "rgba(0, 0, 0, 0.87)",
          "padding": "4px",
          "settings": {
            "enableSelection": true,
            "enableSearch": true,
            "displayDetails": true,
            "allowAcknowledgment": true,
            "allowClear": true,
            "displayPagination": true,
            "defaultPageSize": 10,
            "defaultSortOrder": "-createdTime",
            "enableSelectColumnDisplay": true,
            "enableStickyAction": false,
            "enableFilter": true
          },
          "title": "New Alarms table",
          "dropShadow": true,
          "enableFullscreen": true,
          "titleStyle": {
            "fontSize": "16px",
            "fontWeight": 400,
            "padding": "5px 10px 5px 10px"
          },
          "useDashboardTimewindow": false,
          "showLegend": false,
          "alarmSource": {
            "type": "entity",
            "name": null,
            "entityAliasId": "34c859bf-95f3-7c64-da8a-b5351c3d4281",
            "filterId": null,
            "dataKeys": [
              {
                "name": "createdTime",
                "type": "alarm",
                "label": "Created time",
                "color": "#2196f3",
                "settings": {
                  "useCellStyleFunction": false,
                  "cellStyleFunction": "",
                  "useCellContentFunction": false,
                  "cellContentFunction": ""
                },
                "_hash": 0.021092237451093787
              },
              {
                "name": "originator",
                "type": "alarm",
                "label": "Originator",
                "color": "#4caf50",
                "settings": {
                  "useCellStyleFunction": false,
                  "cellStyleFunction": "",
                  "useCellContentFunction": false,
                  "cellContentFunction": ""
                },
                "_hash": 0.2780007688856758
              },
              {
                "name": "type",
                "type": "alarm",
                "label": "Type",
                "color": "#f44336",
                "settings": {
                  "useCellStyleFunction": false,
                  "cellStyleFunction": "",
                  "useCellContentFunction": false,
                  "cellContentFunction": ""
                },
                "_hash": 0.7323586880398418
              },
              {
                "name": "severity",
                "type": "alarm",
                "label": "Severity",
                "color": "#ffc107",
                "settings": {
                  "useCellStyleFunction": false,
                  "useCellContentFunction": false
                },
                "_hash": 0.09927019860088193
              },
              {
                "name": "status",
                "type": "alarm",
                "label": "Status",
                "color": "#607d8b",
                "settings": {
                  "useCellStyleFunction": false,
                  "cellStyleFunction": "",
                  "useCellContentFunction": false,
                  "cellContentFunction": ""
                },
                "_hash": 0.6588418951443418
              },
              {
                "name": "details.Cuenta",
                "type": "alarm",
                "label": "Cuenta",
                "color": "#9c27b0",
                "settings": {},
                "_hash": 0.9838277137735993,
                "aggregationType": null,
                "units": null,
                "decimals": null,
                "funcBody": null,
                "usePostProcessing": null,
                "postFuncBody": null
              }
            ]
          },
          "alarmSearchStatus": "ANY",
          "alarmsPollingInterval": 5,
          "showTitleIcon": false,
          "titleIcon": "more_horiz",
          "iconColor": "rgba(0, 0, 0, 0.87)",
          "iconSize": "24px",
          "titleTooltip": "",
          "widgetStyle": {},
          "displayTimewindow": true,
          "actions": {},
          "alarmStatusList": [],
          "alarmSeverityList": [],
          "alarmTypeList": [],
          "searchPropagatedAlarms": false,
          "datasources": []
        },
        "row": 0,
        "col": 0,
        "id": "068d8187-65e0-8253-58c4-ff784dfd2948"
      },
      "72f57229-6815-0991-15c8-4159f033f75d": {
        "isSystemType": true,
        "bundleAlias": "digital_gauges",
        "typeAlias": "simple_gauge_justgage",
        "type": "latest",
        "title": "New widget",
        "image": null,
        "description": null,
        "sizeX": 2,
        "sizeY": 2,
        "config": {
          "datasources": [
            {
              "type": "entity",
              "name": null,
              "entityAliasId": "34c859bf-95f3-7c64-da8a-b5351c3d4281",
              "filterId": null,
              "dataKeys": [
                {
                  "name": "Nivel_agua",
                  "type": "timeseries",
                  "label": "Nivel_agua",
                  "color": "#2196f3",
                  "settings": {},
                  "_hash": 0.6590734963315983
                }
              ]
            }
          ],
          "timewindow": {
            "displayValue": "",
            "selectedTab": 0,
            "realtime": {
              "realtimeType": 1,
              "interval": 1000,
              "timewindowMs": 60000,
              "quickInterval": "CURRENT_DAY"
            },
            "history": {
              "historyType": 0,
              "interval": 1000,
              "timewindowMs": 60000,
              "fixedTimewindow": {
                "startTimeMs": 1674305929900,
                "endTimeMs": 1674392329900
              },
              "quickInterval": "CURRENT_DAY"
            },
            "aggregation": {
              "type": "AVG",
              "limit": 2500
            }
          },
          "showTitle": false,
          "backgroundColor": "#ffffff",
          "color": "rgba(0, 0, 0, 0.87)",
          "padding": "0px",
          "settings": {
            "minValue": 0,
            "maxValue": 1,
            "gaugeType": "donut",
            "donutStartAngle": 90,
            "gaugeWidthScale": 0.75,
            "neonGlowBrightness": 0,
            "dashThickness": 0,
            "roundedLineCap": false,
            "gaugeColor": "#eeeeee",
            "useFixedLevelColor": false,
            "levelColors": [],
            "showTitle": true,
            "title": "Nivel del agua",
            "titleFont": {
              "family": "Roboto",
              "size": 12,
              "style": "normal",
              "weight": "500",
              "color": null
            },
            "showUnitTitle": false,
            "showTimestamp": false,
            "showValue": true,
            "valueFont": {
              "family": "Roboto",
              "style": "normal",
              "weight": "500",
              "size": 32,
              "color": "#666666"
            },
            "showMinMax": false,
            "showTicks": false,
            "animation": true,
            "animationDuration": 500,
            "animationRule": "linear"
          },
          "title": "Nivel del agua",
          "dropShadow": true,
          "enableFullscreen": true,
          "titleStyle": {
            "fontSize": "16px",
            "fontWeight": 400
          },
          "useDashboardTimewindow": true,
          "widgetStyle": {},
          "widgetCss": "",
          "pageSize": 1024,
          "decimals": 0,
          "noDataDisplayMessage": "",
          "showLegend": false,
          "showTitleIcon": false,
          "titleTooltip": ""
        },
        "row": 0,
        "col": 0,
        "id": "72f57229-6815-0991-15c8-4159f033f75d"
      },
      "f67b7365-198c-d66f-29c0-2b4d9b27e38a": {
        "isSystemType": true,
        "bundleAlias": "charts",
        "typeAlias": "basic_timeseries",
        "type": "timeseries",
        "title": "New widget",
        "image": null,
        "description": null,
        "sizeX": 8,
        "sizeY": 5,
        "config": {
          "datasources": [
            {
              "type": "entity",
              "name": null,
              "entityAliasId": "34c859bf-95f3-7c64-da8a-b5351c3d4281",
              "filterId": null,
              "dataKeys": [
                {
                  "name": "Electroconductividad",
                  "type": "timeseries",
                  "label": "Electroconductividad",
                  "color": "#e3e348",
                  "settings": {},
                  "_hash": 0.8227446638327363
                },
                {
                  "name": "Temperatura",
                  "type": "timeseries",
                  "label": "Temperatura",
                  "color": "#ff4e2f",
                  "settings": {},
                  "_hash": 0.2381024828486631
                },
                {
                  "name": "Nivel_agua",
                  "type": "timeseries",
                  "label": "Nivel_agua",
                  "color": "#369ff4",
                  "settings": {
                    "hideDataByDefault": false,
                    "disableDataHiding": false,
                    "removeFromLegend": false,
                    "excludeFromStacking": false,
                    "showLines": true,
                    "lineWidth": 3,
                    "fillLines": true,
                    "showPoints": false,
                    "showSeparateAxis": false,
                    "axisPosition": "left",
                    "comparisonSettings": {
                      "showValuesForComparison": true,
                      "comparisonValuesLabel": "",
                      "color": ""
                    },
                    "thresholds": []
                  },
                  "_hash": 0.2610583619269842,
                  "aggregationType": null,
                  "units": null,
                  "decimals": null,
                  "funcBody": null,
                  "usePostProcessing": null,
                  "postFuncBody": null
                }
              ],
              "latestDataKeys": []
            }
          ],
          "timewindow": {
            "hideInterval": false,
            "hideLastInterval": false,
            "hideQuickInterval": false,
            "hideAggregation": false,
            "hideAggInterval": false,
            "hideTimezone": false,
            "selectedTab": 0,
            "realtime": {
              "realtimeType": 0,
              "timewindowMs": 1800000,
              "quickInterval": "CURRENT_DAY",
              "interval": 5000
            },
            "aggregation": {
              "type": "AVG",
              "limit": 2500
            }
          },
          "showTitle": true,
          "backgroundColor": "#fff",
          "color": "rgba(0, 0, 0, 0.87)",
          "padding": "8px",
          "settings": {
            "shadowSize": 4,
            "fontColor": "#545454",
            "fontSize": 10,
            "xaxis": {
              "showLabels": true,
              "color": "#545454"
            },
            "yaxis": {
              "showLabels": true,
              "color": "#545454"
            },
            "grid": {
              "color": "#545454",
              "tickColor": "#DDDDDD",
              "verticalLines": true,
              "horizontalLines": true,
              "outlineWidth": 1
            },
            "legend": {
              "show": true,
              "position": "nw",
              "backgroundColor": "#f0f0f0",
              "backgroundOpacity": 0.85,
              "labelBoxBorderColor": "rgba(1, 1, 1, 0.45)"
            },
            "decimals": 1,
            "stack": false,
            "tooltipIndividual": false
          },
          "title": "Hist贸rico de Temperatura y Electroconductividad",
          "dropShadow": true,
          "enableFullscreen": true,
          "titleStyle": {
            "fontSize": "16px",
            "fontWeight": 400
          },
          "useDashboardTimewindow": false,
          "showTitleIcon": false,
          "titleTooltip": "",
          "widgetStyle": {},
          "widgetCss": "",
          "pageSize": 1024,
          "noDataDisplayMessage": "",
          "showLegend": true,
          "legendConfig": {
            "direction": "column",
            "position": "bottom",
            "sortDataKeys": false,
            "showMin": false,
            "showMax": false,
            "showAvg": true,
            "showTotal": false,
            "showLatest": false
          },
          "displayTimewindow": true
        },
        "row": 0,
        "col": 0,
        "id": "f67b7365-198c-d66f-29c0-2b4d9b27e38a"
      }
    },
    "states": {
      "default": {
        "name": "Huerto Hidrop贸nico",
        "root": true,
        "layouts": {
          "main": {
            "widgets": {
              "eb9cd148-fe64-9230-9a9a-3eda49a524d2": {
                "sizeX": 11,
                "sizeY": 4,
                "row": 0,
                "col": 0
              },
              "734af6a5-39ac-5637-c5a7-3bff34d1b5c6": {
                "sizeX": 9,
                "sizeY": 4,
                "row": 0,
                "col": 16
              },
              "068d8187-65e0-8253-58c4-ff784dfd2948": {
                "sizeX": 11,
                "sizeY": 7,
                "row": 4,
                "col": 14
              },
              "72f57229-6815-0991-15c8-4159f033f75d": {
                "sizeX": 5,
                "sizeY": 4,
                "row": 0,
                "col": 11
              },
              "f67b7365-198c-d66f-29c0-2b4d9b27e38a": {
                "sizeX": 14,
                "sizeY": 7,
                "row": 4,
                "col": 0
              }
            },
            "gridSettings": {
              "backgroundColor": "#eeeeee",
              "columns": 24,
              "margin": 10,
              "backgroundSizeMode": "100%"
            }
          }
        }
      }
    },
    "entityAliases": {
      "34c859bf-95f3-7c64-da8a-b5351c3d4281": {
        "id": "34c859bf-95f3-7c64-da8a-b5351c3d4281",
        "alias": "ESP-32",
        "filter": {
          "type": "singleEntity",
          "resolveMultiple": false,
          "singleEntity": {
            "entityType": "DEVICE",
            "id": "f16c1160-972c-11ed-a3a7-a370cc0b9cb6"
          }
        }
      }
    },
    "filters": {},
    "timewindow": {
      "displayValue": "",
      "hideInterval": false,
      "hideLastInterval": false,
      "hideQuickInterval": false,
      "hideAggregation": false,
      "hideAggInterval": false,
      "hideTimezone": false,
      "selectedTab": 0,
      "realtime": {
        "realtimeType": 0,
        "interval": 1000,
        "timewindowMs": 60000,
        "quickInterval": "CURRENT_DAY"
      },
      "history": {
        "historyType": 0,
        "interval": 1000,
        "timewindowMs": 60000,
        "fixedTimewindow": {
          "startTimeMs": 1673959226435,
          "endTimeMs": 1674045626435
        },
        "quickInterval": "CURRENT_DAY"
      },
      "aggregation": {
        "type": "AVG",
        "limit": 2500
      }
    },
    "settings": {
      "stateControllerId": "entity",
      "showTitle": false,
      "showDashboardsSelect": true,
      "showEntitiesSelect": true,
      "showDashboardTimewindow": true,
      "showDashboardExport": true,
      "toolbarAlwaysOpen": true
    }
  },
  "externalId": null,
  "name": "Huerto Hidrop贸nico"
}